urlextract/__init__.py
urlextract/cachefile.py
urlextract/urlextract_core.py
urlextract/data/tlds-alpha-by-domain.txt
urlextract-1.8.0.dist-info/LICENSE
urlextract-1.8.0.dist-info/METADATA
urlextract-1.8.0.dist-info/WHEEL
urlextract-1.8.0.dist-info/entry_points.txt
urlextract-1.8.0.dist-info/top_level.txt
urlextract-1.8.0.dist-info/RECORD
