Metadata-Version: 2.1
Name: urlextract
Version: 1.8.0
Summary: Collects and extracts URLs from given text.
Home-page: https://github.com/lipoja/URLExtract
Author: Jan Lipovský
Author-email: janlipovsky@gmail.com
License: MIT
Project-URL: Documentation, https://urlextract.readthedocs.io/en/latest/
Project-URL: Source Code, https://github.com/lipoja/URLExtract
Keywords: url,extract,find,finder,collect,link,tld,list
Classifier: Development Status :: 5 - Production/Stable
Classifier: Intended Audience :: Developers
Classifier: License :: OSI Approved :: MIT License
Classifier: Programming Language :: Python
Classifier: Programming Language :: Python :: 3.5
Classifier: Programming Language :: Python :: 3.6
Classifier: Programming Language :: Python :: 3.7
Classifier: Programming Language :: Python :: 3.8
Classifier: Programming Language :: Python :: 3.9
Classifier: Programming Language :: Python :: 3.10
Classifier: Programming Language :: Python :: 3.11
Classifier: Topic :: Text Processing
Classifier: Topic :: Text Processing :: Markup :: HTML
Classifier: Topic :: Software Development :: Libraries :: Python Modules
License-File: LICENSE
